mkdocs_git_committers_plugin/__init__.py
mkdocs_git_committers_plugin/plugin.py
mkdocs_git_committers_plugin_3-0.2.8.dist-info/LICENSE
mkdocs_git_committers_plugin_3-0.2.8.dist-info/METADATA
mkdocs_git_committers_plugin_3-0.2.8.dist-info/WHEEL
mkdocs_git_committers_plugin_3-0.2.8.dist-info/entry_points.txt
mkdocs_git_committers_plugin_3-0.2.8.dist-info/top_level.txt
mkdocs_git_committers_plugin_3-0.2.8.dist-info/RECORD
