Metadata-Version: 2.2
Name: mkdocs-git-committers-plugin-3
Version: 0.2.8
Summary: An MkDocs plugin to create a list of contributors on the page
Home-page: https://github.com/byrnereese/mkdocs-git-committers-plugin/
Author: Byrne Reese
Author-email: byrne@majordojo.com
License: MIT
Keywords: mkdocs pdf github
Classifier: Development Status :: 4 - Beta
Classifier: Intended Audience :: Developers
Classifier: Intended Audience :: Information Technology
Classifier: License :: OSI Approved :: MIT License
Classifier: Programming Language :: Python
Classifier: Programming Language :: Python :: 3 :: Only
Classifier: Programming Language :: Python :: 3.4
Classifier: Programming Language :: Python :: 3.5
Classifier: Programming Language :: Python :: 3.6
Classifier: Programming Language :: Python :: 3.7
Requires-Python: >=3.5
License-File: LICENSE
Requires-Dist: PyGithub>=1.43
Requires-Dist: mkdocs>=0.17
Dynamic: author
Dynamic: author-email
Dynamic: classifier
Dynamic: description
Dynamic: home-page
Dynamic: keywords
Dynamic: license
Dynamic: requires-dist
Dynamic: requires-python
Dynamic: summary
